alcherializer/__init__.py
alcherializer/exceptions.py
alcherializer/fields.py
alcherializer/serializer.py
alcherializer-0.5.0.dist-info/METADATA
alcherializer-0.5.0.dist-info/WHEEL
alcherializer-0.5.0.dist-info/top_level.txt
alcherializer-0.5.0.dist-info/RECORD
