Metadata-Version: 2.1
Name: alcherializer
Version: 0.5.0
Summary: Django like model serializer
Home-page: https://github.com/vinyguedess/alcherializer
Author: Vinicius Guedes
Author-email: viniciusgued@gmail.com
License: MIT
Download-URL: https://github.com/vinyguedess/alcherializer/archive/master.zip
Keywords: django,flask,serializer,sql,sqlalchemy,alchemy
Platform: UNKNOWN
Classifier: Development Status :: 5 - Production/Stable
Classifier: Intended Audience :: Developers
Classifier: Topic :: Software Development :: Build Tools
Classifier: License :: OSI Approved :: MIT License
Classifier: Programming Language :: Python :: 3.6
Classifier: Programming Language :: Python :: 3.7
Classifier: Programming Language :: Python :: 3.8
Requires-Dist: SQLAlchemy (<=1.4.18,>=1.3.20)
